floxs/__init__.py
floxs/common/__init__.py
floxs/common/utils.py
floxs/flock/__init__.py
floxs/flock/env.py
floxs/flock/generator.py
floxs/flock/observations.py
floxs/flock/rewards.py
floxs/flock/types.py
floxs/flock/viewer.py
floxs/predator_prey/__init__.py
floxs/predator_prey/env.py
floxs/predator_prey/generator.py
floxs/predator_prey/observations.py
floxs/predator_prey/rewards.py
floxs/predator_prey/types.py
floxs/predator_prey/viewer.py
floxs-0.1.1.dist-info/LICENSE.txt
floxs-0.1.1.dist-info/METADATA
floxs-0.1.1.dist-info/WHEEL
floxs-0.1.1.dist-info/RECORD
