Metadata-Version: 2.1
Name: floxs
Version: 0.1.1
Summary: Multi-agent RL flock and swarm environments implemented in JAX
Home-page: https://zombie-einstein.github.io/floxs
License: MIT
Keywords: simulation,reinforcement-learning
Author: zombie-einstein
Author-email: zombie-einstein@proton.me
Requires-Python: >=3.10,<3.12
Classifier: Development Status :: 4 - Beta
Classifier: Environment :: GPU
Classifier: Intended Audience :: Science/Research
Classifier: License :: OSI Approved :: MIT License
Classifier: Programming Language :: Python
Classifier: Programming Language :: Python :: 3
Classifier: Programming Language :: Python :: 3.10
Classifier: Programming Language :: Python :: 3.11
Classifier: Programming Language :: Python :: 3.12
Classifier: Programming Language :: Python :: Implementation :: CPython
Classifier: Programming Language :: Python :: Implementation :: PyPy
Classifier: Topic :: Scientific/Engineering :: Artificial Intelligence
Classifier: Topic :: Scientific/Engineering :: Artificial Life
Requires-Dist: chex (>=0.1.6,<0.2.0)
Requires-Dist: esquilax (>=2.0.0)
Requires-Dist: jax (>=0.4.4,<0.5.0)
Requires-Dist: jumanji (>=1.1.1,<2.0.0)
Project-URL: Documentation, https://zombie-einstein.github.io/floxs
Project-URL: Repository, https://github.com/zombie-einstein/floxs
